COPYRIGHT.txt
LICENSE.txt
MANIFEST.in
README.txt
eggtestinfo-0.2.2-py2.6.egg
setup.py
Products/__init__.py
Products.CMFCalendar.egg-info/PKG-INFO
Products.CMFCalendar.egg-info/SOURCES.txt
Products.CMFCalendar.egg-info/dependency_links.txt
Products.CMFCalendar.egg-info/entry_points.txt
Products.CMFCalendar.egg-info/namespace_packages.txt
Products.CMFCalendar.egg-info/not-zip-safe
Products.CMFCalendar.egg-info/requires.txt
Products.CMFCalendar.egg-info/test_info.txt
Products.CMFCalendar.egg-info/top_level.txt
Products/CMFCalendar/CHANGES.txt
Products/CMFCalendar/COPYRIGHT.txt
Products/CMFCalendar/CREDITS.txt
Products/CMFCalendar/CalendarTool.py
Products/CMFCalendar/Event.py
Products/CMFCalendar/README.txt
Products/CMFCalendar/__init__.py
Products/CMFCalendar/configure.zcml
Products/CMFCalendar/exceptions.py
Products/CMFCalendar/permissions.py
Products/CMFCalendar/setuphandlers.py
Products/CMFCalendar/testing.py
Products/CMFCalendar/tool.gif
Products/CMFCalendar/utils.py
Products/CMFCalendar/version.txt
Products/CMFCalendar/browser/__init__.py
Products/CMFCalendar/browser/calendartool.py
Products/CMFCalendar/browser/configure.zcml
Products/CMFCalendar/browser/event.py
Products/CMFCalendar/browser/event.txt
Products/CMFCalendar/browser/tests.py
Products/CMFCalendar/browser/templates/calendar_day.pt
Products/CMFCalendar/browser/templates/calendar_widgets.pt
Products/CMFCalendar/browser/templates/event_ical.pt
Products/CMFCalendar/browser/templates/event_vcal.pt
Products/CMFCalendar/browser/templates/event_view.pt
Products/CMFCalendar/interfaces/__init__.py
Products/CMFCalendar/interfaces/_content.py
Products/CMFCalendar/interfaces/_tools.py
Products/CMFCalendar/locales/cmf_calendar-manual.pot
Products/CMFCalendar/locales/cmf_calendar.pot
Products/CMFCalendar/profiles/default/catalog.xml
Products/CMFCalendar/profiles/default/componentregistry.xml
Products/CMFCalendar/profiles/default/toolset.xml
Products/CMFCalendar/profiles/default/types.xml
Products/CMFCalendar/profiles/default/various-calendar.txt
Products/CMFCalendar/profiles/default/types/Event.xml
Products/CMFCalendar/profiles/skins_support/skins.xml
Products/CMFCalendar/profiles/skins_support/types/Event.xml
Products/CMFCalendar/skins/zpt_calendar/CalendarStyle.css
Products/CMFCalendar/skins/zpt_calendar/calendarBox.pt
Products/CMFCalendar/skins/zpt_calendar/calendar_day_view.py
